rdpurchaseorder/EcsInterface.py
rdpurchaseorder/__init__.py
rdpurchaseorder/mainModel.py
rdpurchaseorder/metadata.py
rdpurchaseorder/operation.py
rdpurchaseorder/utility.py
rdpurchaseorder-1.3.4.dist-info/METADATA
rdpurchaseorder-1.3.4.dist-info/WHEEL
rdpurchaseorder-1.3.4.dist-info/top_level.txt
rdpurchaseorder-1.3.4.dist-info/RECORD
